{
  "file": "./models/readings.json",
  "readings": [
    {
      "date": "2023-08-17 13:40:25",
      "code": 7,
      "temperature": 8,
      "windSpeed": 9,
      "pressure": 7,
      "_id": "d0790360-2f5e-421c-8df2-e9718601da6a",
      "stationid": "9ed630e4-d4e3-404d-af40-6b534e16b880"
    },
    {
      "date": "2023-08-17 13:40:25",
      "code": 3,
      "temperature": 141,
      "windSpeed": 1,
      "pressure": 1,
      "_id": "053cb06d-490b-41e6-846f-e2a41e661b67",
      "stationid": "ae7f75b1-ecc8-4cf7-90ee-5c14d17c061a"
    },
    {
      "date": "2023-08-17 13:40:25",
      "code": 3,
      "temperature": 2,
      "windSpeed": 2,
      "pressure": 2,
      "_id": "d57f4c8c-2ed4-43ad-b310-7666b3312a0f",
      "stationid": "ae7f75b1-ecc8-4cf7-90ee-5c14d17c061a"
    },
    {
      "date": "2023-08-17 13:40:25",
      "code": 3,
      "temperature": 3,
      "windSpeed": 3,
      "pressure": 3,
      "_id": "83816be0-7fc7-4dbf-9b3c-8b0a41538601",
      "stationid": "ae7f75b1-ecc8-4cf7-90ee-5c14d17c061a"
    },
    {
      "date": "2023-08-17 13:40:25",
      "code": 800,
      "temperature": 0.5,
      "windSpeed": 3.5,
      "pressure": 1002,
      "_id": "f6bf90bd-b8ee-41bf-8b23-90fbdf451322",
      "stationid": "961fdacc-2f2c-4623-849b-d021a0be0883"
    },
    {
      "date": "2023-08-17 13:42:41",
      "code": 4,
      "temperature": 4,
      "windSpeed": 4,
      "windDirection": 4,
      "pressure": 4,
      "_id": "569e46eb-ae56-48e0-a04a-c5123d03d48f",
      "stationid": "90adb9cb-8671-4cca-ac44-b7f5bfa422a8"
    },
    {
      "date": "2023-08-23 15:45:50",
      "code": 700,
      "temperature": 0,
      "windSpeed": 0,
      "windDirection": 0,
      "pressure": 0,
      "_id": "9b39a06a-382e-424e-928d-da9166250313",
      "stationid": "b5810ba9-fea4-4a2c-a80c-7228475eaf45"
    },
    {
      "date": "2023-08-24 20:01:47",
      "code": 803,
      "temperature": 25.65,
      "windSpeed": 4.8,
      "windDirection": 190,
      "pressure": 1012,
      "tempTrend": [
        25.7,
        26.01,
        25.31,
        24.91,
        24.92,
        24.83,
        25.02,
        24.97
      ],
      "trendLabels": [
        "24/7/2023",
        "25/7/2023",
        "26/7/2023",
        "27/7/2023",
        "28/7/2023",
        "29/7/2023",
        "30/7/2023",
        "31/7/2023"
      ],
      "_id": "aa749c85-a3c9-4d19-96ea-d1069dc264c1",
      "stationid": "72766cbe-90eb-41b3-a413-24ad85c0e02f"
    },
    {
      "date": "2023-08-28 10:53:02",
      "code": 1,
      "temperature": 1,
      "windSpeed": 1,
      "windDirection": 1,
      "pressure": 1,
      "_id": "7d2d67e4-9161-4a3c-a9c9-bf7e961540d1",
      "stationid": "1b03b659-65ab-4d80-87ef-2a607b3dd9a9"
    },
    {
      "date": "2023-08-28 10:53:08",
      "code": 2,
      "temperature": 2,
      "windSpeed": 2,
      "windDirection": 2,
      "pressure": 2,
      "_id": "b067a4b4-d9bd-4a00-bf4d-eb9530c3e9cf",
      "stationid": "1b03b659-65ab-4d80-87ef-2a607b3dd9a9"
    },
    {
      "date": "2023-08-28 10:53:15",
      "code": 3,
      "temperature": 3,
      "windSpeed": 3,
      "windDirection": 3,
      "pressure": 3,
      "_id": "403404cb-d3b3-4761-a62d-81a7f5d3f7c6",
      "stationid": "1b03b659-65ab-4d80-87ef-2a607b3dd9a9"
    },
    {
      "date": "2023-08-28 12:37:01",
      "code": 802,
      "temperature": 37.6,
      "windSpeed": 7.04,
      "windDirection": 311,
      "pressure": 999,
      "tempTrend": [
        36.78,
        35.53,
        34.68,
        33.82,
        34.73,
        37.54,
        33.81,
        33.72
      ],
      "trendLabels": [
        "28/8/2023",
        "29/8/2023",
        "30/8/2023",
        "31/8/2023",
        "1/9/2023",
        "2/9/2023",
        "3/9/2023",
        "4/9/2023"
      ],
      "_id": "e64ea5f4-501f-4143-9a99-dd48a06d5850",
      "stationid": "1b03b659-65ab-4d80-87ef-2a607b3dd9a9"
    },
    {
      "date": "2023-08-28 14:44:26",
      "code": 801,
      "temperature": 35.16,
      "windSpeed": 2.6,
      "windDirection": 304,
      "pressure": 1000,
      "tempTrend": [
        36.78,
        35.53,
        34.68,
        33.82,
        34.73,
        37.54,
        33.81,
        33.72
      ],
      "trendLabels": [
        "28/8/2023",
        "29/8/2023",
        "30/8/2023",
        "31/8/2023",
        "1/9/2023",
        "2/9/2023",
        "3/9/2023",
        "4/9/2023"
      ],
      "_id": "d6ed54c6-ca6f-4d09-8ef1-2c99627d675e",
      "stationid": "1b03b659-65ab-4d80-87ef-2a607b3dd9a9"
    },
    {
      "date": "2023-08-28 16:02:27",
      "code": 804,
      "temperature": 25.61,
      "windSpeed": 5.7,
      "windDirection": 202,
      "pressure": 1013,
      "tempTrend": [
        25.49,
        25.05,
        25.19,
        25.28,
        25.12,
        25.22,
        25.02,
        24.83
      ],
      "trendLabels": [
        "28/8/2023",
        "29/8/2023",
        "30/8/2023",
        "31/8/2023",
        "1/9/2023",
        "2/9/2023",
        "3/9/2023",
        "4/9/2023"
      ],
      "windTrend": [
        5.73,
        6.92,
        6.99,
        7.1,
        7.6,
        7.84,
        8.91,
        6.36
      ],
      "_id": "e1360a11-7f81-4f7c-a830-4656e9f15df8",
      "stationid": "72766cbe-90eb-41b3-a413-24ad85c0e02f"
    },
    {
      "date": "2023-08-28 16:41:47",
      "code": 400,
      "temperature": 25.63,
      "windSpeed": 5.53,
      "windDirection": 197,
      "pressure": 1013,
      "tempTrend": [
        25.46,
        25.05,
        25.19,
        25.28,
        25.12,
        25.22,
        25.02,
        24.83
      ],
      "trendLabels": [
        "28/8/2023",
        "29/8/2023",
        "30/8/2023",
        "31/8/2023",
        "1/9/2023",
        "2/9/2023",
        "3/9/2023",
        "4/9/2023"
      ],
      "windTrend": [
        5.73,
        6.92,
        6.99,
        7.1,
        7.6,
        7.84,
        8.91,
        6.36
      ],
      "pressureTrend": [
        1015,
        1016,
        1015,
        1016,
        1016,
        1016,
        1016,
        1017
      ],
      "_id": "f5215a99-4c23-49ad-9dee-d44479d51142",
      "stationid": "72766cbe-90eb-41b3-a413-24ad85c0e02f"
    },
    {
      "date": "2023-08-29 10:58:47",
      "code": 700,
      "temperature": 8,
      "windSpeed": 1,
      "windDirection": 98,
      "pressure": 999,
      "tempTrend": [
        16.8,
        15.35,
        17.78,
        17.12,
        17.61,
        17.73,
        17.09,
        16.63
      ],
      "windTrend": [
        6.98,
        6.57,
        6.4,
        3.75,
        5.6,
        5.64,
        4.93,
        6.98
      ],
      "pressureTrend": [
        1013,
        1011,
        1005,
        1012,
        1023,
        1022,
        1017,
        1017
      ],
      "trendLabels": [
        "29/8/2023",
        "30/8/2023",
        "31/8/2023",
        "1/9/2023",
        "2/9/2023",
        "3/9/2023",
        "4/9/2023",
        "5/9/2023"
      ],
      "_id": "11bb177c-0065-4b5f-a97f-c38deb252179",
      "stationid": "05"
    },
    {
      "date": "2023-08-29 10:59:16",
      "code": 200,
      "temperature": 0.5,
      "windSpeed": 3.5,
      "windDirection": 102,
      "pressure": 1000,
      "tempTrend": [
        16.8,
        15.35,
        17.78,
        17.12,
        17.61,
        17.73,
        17.09,
        16.63
      ],
      "windTrend": [
        6.98,
        6.57,
        6.4,
        3.75,
        5.6,
        5.64,
        4.93,
        6.98
      ],
      "pressureTrend": [
        1013,
        1011,
        1005,
        1012,
        1023,
        1022,
        1017,
        1017
      ],
      "trendLabels": [
        "29/8/2023",
        "30/8/2023",
        "31/8/2023",
        "1/9/2023",
        "2/9/2023",
        "3/9/2023",
        "4/9/2023",
        "5/9/2023"
      ],
      "_id": "ce4e11ab-d2a3-4e47-8049-c41a6b0b8342",
      "stationid": "05"
    },
    {
      "date": "2023-08-29 15:39:46",
      "code": 800,
      "temperature": 0.5,
      "windSpeed": 3.5,
      "windDirection": 90,
      "pressure": 1002,
      "tempTrend": [
        16.78,
        15.72,
        18.12,
        16.56,
        17.59,
        18.3,
        18.01,
        15.48
      ],
      "windTrend": [
        6.64,
        6.6,
        6.52,
        3.21,
        4.98,
        4.25,
        6.55,
        6.74
      ],
      "pressureTrend": [
        1013,
        1011,
        1005,
        1013,
        1023,
        1022,
        1017,
        1019
      ],
      "trendLabels": [
        "29/8/2023",
        "30/8/2023",
        "31/8/2023",
        "1/9/2023",
        "2/9/2023",
        "3/9/2023",
        "4/9/2023",
        "5/9/2023"
      ],
      "_id": "2a2124a4-10a0-452e-b69b-6b0d1c926f2c",
      "stationid": "01"
    },
    {
      "date": "2023-08-29 15:40:08",
      "code": 600,
      "temperature": 6,
      "windSpeed": 2,
      "windDirection": 96,
      "pressure": 1004,
      "tempTrend": [
        16.78,
        15.72,
        18.12,
        16.56,
        17.59,
        18.3,
        18.01,
        15.48
      ],
      "windTrend": [
        6.64,
        6.6,
        6.52,
        3.21,
        4.98,
        4.25,
        6.55,
        6.74
      ],
      "pressureTrend": [
        1013,
        1011,
        1005,
        1013,
        1023,
        1022,
        1017,
        1019
      ],
      "trendLabels": [
        "29/8/2023",
        "30/8/2023",
        "31/8/2023",
        "1/9/2023",
        "2/9/2023",
        "3/9/2023",
        "4/9/2023",
        "5/9/2023"
      ],
      "_id": "78723833-aa14-40ea-9616-88a14afd80a4",
      "stationid": "01"
    },
    {
      "date": "2023-08-29 15:40:27",
      "code": 700,
      "temperature": 8,
      "windSpeed": 1,
      "windDirection": 101,
      "pressure": 1005,
      "tempTrend": [
        16.78,
        15.72,
        18.12,
        16.56,
        17.59,
        18.3,
        18.01,
        15.48
      ],
      "windTrend": [
        6.64,
        6.6,
        6.52,
        3.21,
        4.98,
        4.25,
        6.55,
        6.74
      ],
      "pressureTrend": [
        1013,
        1011,
        1005,
        1013,
        1023,
        1022,
        1017,
        1019
      ],
      "trendLabels": [
        "29/8/2023",
        "30/8/2023",
        "31/8/2023",
        "1/9/2023",
        "2/9/2023",
        "3/9/2023",
        "4/9/2023",
        "5/9/2023"
      ],
      "_id": "33ac00df-ce07-4a63-b85f-e9bbc55a4a72",
      "stationid": "01"
    },
    {
      "date": "2023-08-30 09:58:20",
      "code": 500,
      "temperature": 25.01,
      "windSpeed": 0.26,
      "windDirection": 229,
      "pressure": 1016,
      "tempTrend": [
        25.97,
        29.01,
        26.98,
        30.19,
        29.81,
        23.09,
        27.72,
        28.55
      ],
      "trendLabels": [
        "30/8/2023",
        "31/8/2023",
        "1/9/2023",
        "2/9/2023",
        "3/9/2023",
        "4/9/2023",
        "5/9/2023",
        "6/9/2023"
      ],
      "windTrend": [
        1.26,
        3.18,
        2.8,
        3.05,
        1.72,
        1.66,
        1.27,
        1.33
      ],
      "pressureTrend": [
        1016,
        1016,
        1015,
        1013,
        1013,
        1015,
        1013,
        1014
      ],
      "_id": "c8d1d817-07fc-4235-9f6e-ccc0621cb605",
      "stationid": "60d17548-6566-4aba-8b81-f7c6d939ee38"
    },
    {
      "date": "2023-08-30 10:00:42",
      "code": 20,
      "temperature": 20,
      "windSpeed": 203,
      "windDirection": 203,
      "pressure": 103,
      "tempTrend": [
        25.97,
        29.01,
        26.98,
        30.19,
        29.81,
        23.09,
        27.72,
        28.55
      ],
      "windTrend": [
        1.26,
        3.18,
        2.8,
        3.05,
        1.72,
        1.66,
        1.27,
        1.33
      ],
      "pressureTrend": [
        1016,
        1016,
        1015,
        1013,
        1013,
        1015,
        1013,
        1014
      ],
      "trendLabels": [
        "30/8/2023",
        "31/8/2023",
        "1/9/2023",
        "2/9/2023",
        "3/9/2023",
        "4/9/2023",
        "5/9/2023",
        "6/9/2023"
      ],
      "_id": "5b68812f-42c3-42ac-91ff-8a735b3d8cfc",
      "stationid": "60d17548-6566-4aba-8b81-f7c6d939ee38"
    },
    {
      "date": "2023-08-30 10:02:49",
      "code": 500,
      "temperature": 25.01,
      "windSpeed": 0.26,
      "windDirection": 229,
      "pressure": 1016,
      "tempTrend": [
        25.97,
        29.01,
        26.98,
        30.19,
        29.81,
        23.09,
        27.72,
        28.55
      ],
      "trendLabels": [
        "30/8/2023",
        "31/8/2023",
        "1/9/2023",
        "2/9/2023",
        "3/9/2023",
        "4/9/2023",
        "5/9/2023",
        "6/9/2023"
      ],
      "windTrend": [
        1.26,
        3.18,
        2.8,
        3.05,
        1.72,
        1.66,
        1.27,
        1.33
      ],
      "pressureTrend": [
        1016,
        1016,
        1015,
        1013,
        1013,
        1015,
        1013,
        1014
      ],
      "_id": "3a06988c-2a64-4c51-b833-01550f7a0298",
      "stationid": "60d17548-6566-4aba-8b81-f7c6d939ee38"
    },
    {
      "date": "2023-08-30 10:04:52",
      "code": 500,
      "temperature": 25.01,
      "windSpeed": 0.26,
      "windDirection": 229,
      "pressure": 1016,
      "tempTrend": [
        25.97,
        29.01,
        26.98,
        30.19,
        29.81,
        23.09,
        27.72,
        28.55
      ],
      "trendLabels": [
        "30/8/2023",
        "31/8/2023",
        "1/9/2023",
        "2/9/2023",
        "3/9/2023",
        "4/9/2023",
        "5/9/2023",
        "6/9/2023"
      ],
      "windTrend": [
        1.26,
        3.18,
        2.8,
        3.05,
        1.72,
        1.66,
        1.27,
        1.33
      ],
      "pressureTrend": [
        1016,
        1016,
        1015,
        1013,
        1013,
        1015,
        1013,
        1014
      ],
      "_id": "43dc1ced-3e2d-442d-9560-5b9ea3c1297d",
      "stationid": "60d17548-6566-4aba-8b81-f7c6d939ee38"
    },
    {
      "date": "2023-08-30 10:06:18",
      "code": 500,
      "temperature": 25.01,
      "windSpeed": 0.26,
      "windDirection": 229,
      "pressure": 1016,
      "tempTrend": [
        25.97,
        29.01,
        26.98,
        30.19,
        29.81,
        23.09,
        27.72,
        28.55
      ],
      "trendLabels": [
        "30/8/2023",
        "31/8/2023",
        "1/9/2023",
        "2/9/2023",
        "3/9/2023",
        "4/9/2023",
        "5/9/2023",
        "6/9/2023"
      ],
      "windTrend": [
        1.26,
        3.18,
        2.8,
        3.05,
        1.72,
        1.66,
        1.27,
        1.33
      ],
      "pressureTrend": [
        1016,
        1016,
        1015,
        1013,
        1013,
        1015,
        1013,
        1014
      ],
      "_id": "8be15dd5-659a-4a51-acb5-140ea561758a",
      "stationid": "60d17548-6566-4aba-8b81-f7c6d939ee38"
    },
    {
      "date": "2023-08-30 10:07:06",
      "code": 40,
      "temperature": 62,
      "windSpeed": 83,
      "windDirection": 930,
      "pressure": 28,
      "tempTrend": [
        25.97,
        29.01,
        26.98,
        30.19,
        29.81,
        23.09,
        27.72,
        28.55
      ],
      "windTrend": [
        1.26,
        3.18,
        2.8,
        3.05,
        1.72,
        1.66,
        1.27,
        1.33
      ],
      "pressureTrend": [
        1016,
        1016,
        1015,
        1013,
        1013,
        1015,
        1013,
        1014
      ],
      "trendLabels": [
        "30/8/2023",
        "31/8/2023",
        "1/9/2023",
        "2/9/2023",
        "3/9/2023",
        "4/9/2023",
        "5/9/2023",
        "6/9/2023"
      ],
      "_id": "3bd0eb69-657e-4a7e-bde9-203364d0ccaf",
      "stationid": "60d17548-6566-4aba-8b81-f7c6d939ee38"
    },
    {
      "date": "2023-08-30 10:21:52",
      "code": 31,
      "temperature": 31,
      "windSpeed": 31,
      "windDirection": 31,
      "pressure": 31,
      "tempTrend": [
        25.04,
        25.56,
        25.37,
        25.55,
        25.11,
        25.34,
        25.34,
        25.31
      ],
      "windTrend": [
        7.05,
        7,
        8.06,
        8.06,
        8.97,
        6.52,
        6.53,
        7.02
      ],
      "pressureTrend": [
        1016,
        1015,
        1015,
        1015,
        1016,
        1016,
        1015,
        1016
      ],
      "trendLabels": [
        "30/8/2023",
        "31/8/2023",
        "1/9/2023",
        "2/9/2023",
        "3/9/2023",
        "4/9/2023",
        "5/9/2023",
        "6/9/2023"
      ],
      "_id": "c95414ff-efb1-4e10-aa0e-b4c81799c6f0",
      "stationid": "72766cbe-90eb-41b3-a413-24ad85c0e02f"
    }
  ]
}